{"schoolName":"苗栗縣泰安鄉泰興國小","date":"2018/06/11","dayArray":[{"dayCheck":true,"name":"星期一","stapleFood":{"name":"白飯","ingredientArray":[{"name":"白米","unit":"25.8"}]},"mainCourse":{"name":"烤雞","ingredientArray":[{"name":"烤雞","unit":"13"}]},"sideDishOne":{"name":"炒小白菜","ingredientArray":[{"name":"小白菜","unit":"8"}]},"sideDishSecond":{"name":"番茄炒蛋","ingredientArray":[{"name":"番茄","unit":"4"}]},"soup":{"name":"蘿蔔排骨湯","ingredientArray":[{"name":"白蘿蔔","unit":"4"},{"name":"排骨","unit":"4"}]},"acceptanceArray":[{"name":"蒜末","unit":"2斤"},{"name":"蒜仁","unit":"2斤"},{"name":"蔥","unit":"2斤"},{"name":"香菜","unit":"2把"},{"name":"蛋","unit":"1箱"},{"name":"醬油","unit":"1箱"},{"name":"炒手","unit":"3包"}]},{"dayCheck":true,"name":"星期二","stapleFood":{"name":"白飯","ingredientArray":[{"name":"白米","unit":"25.8"}]},"mainCourse":{"name":"三杯鴨肉","ingredientArray":[{"name":"鴨肉","unit":"14"},{"name":"洋蔥","unit":"2"},{"name":"紅籮蔔","unit":"2"}]},"sideDishOne":{"name":"炒菠菜","ingredientArray":[{"name":"菠菜","unit":"8"}]},"sideDishSecond":{"name":"豆干炒小魚乾","ingredientArray":[{"name":"豆干","unit":"8"},{"name":"小魚干","unit":"0.5"}]},"soup":{"name":"海帶吻仔魚湯","ingredientArray":[{"name":"海帶","unit":"3"},{"name":"吻仔魚","unit":"3"}]},"acceptanceArray":[{"name":"九層塔","unit":"0.5包"},{"name":"老薑","unit":"2斤"}]},{"dayCheck":true,"name":"星期三","stapleFood":{"name":"白飯","ingredientArray":[{"name":"白米","unit":"25.8"}]},"mainCourse":{"name":"芋香燒雞","ingredientArray":[{"name":"雞肉丁","unit":"12"},{"name":"芋頭","unit":"3"}]},"sideDishOne":{"name":"炒A菜","ingredientArray":[{"name":"A菜","unit":"8"}]},"sideDishSecond":{"name":"麻婆豆腐","ingredientArray":[{"name":"絞肉","unit":"2"},{"name":"豆腐","unit":"4"}]},"soup":{"name":"仙草湯","ingredientArray":[{"name":"仙草","unit":"5"}]},"acceptanceArray":[]},{"dayCheck":true,"name":"星期四","stapleFood":{"name":"白飯","ingredientArray":[{"name":"白米","unit":"25.8"}]},"mainCourse":{"name":"竹筍炒肉絲","ingredientArray":[{"name":"竹筍","unit":"8"},{"name":"肉絲","unit":"8"}]},"sideDishOne":{"name":"炒油菜","ingredientArray":[{"name":"油菜","unit":"8"}]},"sideDishSecond":{"name":"三色蒸蛋","ingredientArray":[{"name":"鹹蛋","unit":"4"},{"name":"皮蛋","unit":"4"}]},"soup":{"name":"肉羹湯","ingredientArray":[{"name":"肉羹","unit":"5"}]},"acceptanceArray":[{"name":"蔥","unit":"3斤"},{"name":"蒜末","unit":"3斤"},{"name":"蒜仁","unit":"2斤"},{"name":"香菜","unit":"2把"}]},{"dayCheck":true,"name":"星期五","stapleFood":{"name":"白飯","ingredientArray":[{"name":"白米","unit":"25.8"}]},"mainCourse":{"name":"滷肉","ingredientArray":[{"name":"豬肉丁","unit":"10"}]},"sideDishOne":{"name":"炒高麗菜","ingredientArray":[{"name":"高麗菜","unit":"8"}]},"sideDishSecond":{"name":"金針菇炒小黃瓜","ingredientArray":[{"name":"小黃瓜","unit":"8"},{"name":"金針菇","unit":""}]},"soup":{"name":"玉米濃湯","ingredientArray":[{"name":"玉米罐頭","unit":"4"},{"name":"玉米濃湯粉","unit":"2"}]},"acceptanceArray":[{"name":"滷包","unit":"1包"}]}]}